menovideo/__init__.py
menovideo/menovideo.py
menovideo/version.py
menovideo/videopre.py
menovideo-0.5.1.dist-info/LICENSE
menovideo-0.5.1.dist-info/METADATA
menovideo-0.5.1.dist-info/WHEEL
menovideo-0.5.1.dist-info/top_level.txt
menovideo-0.5.1.dist-info/RECORD
