Metadata-Version: 2.1
Name: menovideo
Version: 0.5.1
Summary: (Unofficial) PyTorch library data efficient video transformer for video understanding and action recognatio 
Home-page: https://github.com/mamonraab/Data-efficient-video-transformer
Author: almamon rasool abdali
Author-email: mamonrasoolabdali@gmail.com
License: UNKNOWN
Keywords: pytorch pretrained video models efficientnet transformer
Platform: UNKNOWN
Classifier: Development Status :: 5 - Production/Stable
Classifier: Intended Audience :: Education
Classifier: Intended Audience :: Science/Research
Classifier: License :: OSI Approved :: Apache Software License
Classifier: Programming Language :: Python :: 3.6
Classifier: Programming Language :: Python :: 3.7
Classifier: Programming Language :: Python :: 3.8
Classifier: Topic :: Scientific/Engineering
Classifier: Topic :: Scientific/Engineering :: Artificial Intelligence
Classifier: Topic :: Software Development
Classifier: Topic :: Software Development :: Libraries
Classifier: Topic :: Software Development :: Libraries :: Python Modules
Requires-Python: >=3.6
License-File: LICENSE
Requires-Dist: torch (>=1.4)
Requires-Dist: torchvision
